openscad_docsgen/__init__.py
openscad_docsgen/blocks.py
openscad_docsgen/errorlog.py
openscad_docsgen/filehashes.py
openscad_docsgen/imagemanager.py
openscad_docsgen/logmanager.py
openscad_docsgen/mdimggen.py
openscad_docsgen/parser.py
openscad_docsgen/target.py
openscad_docsgen/target_githubwiki.py
openscad_docsgen/target_wiki.py
openscad_docsgen/utils.py
openscad_docsgen-2.0.54.dist-info/METADATA
openscad_docsgen-2.0.54.dist-info/WHEEL
openscad_docsgen-2.0.54.dist-info/entry_points.txt
openscad_docsgen-2.0.54.dist-info/licenses/LICENSE
openscad_docsgen-2.0.54.dist-info/RECORD
