Metadata-Version: 2.4
Name: openscad_docsgen
Version: 2.0.54
Summary: A processor to generate Markdown code documentation with images from OpenSCAD source comments.
Project-URL: Homepage, https://github.com/belfryscad/openscad_docsgen
Project-URL: Repository, https://github.com/belfryscad/openscad_docsgen
Project-URL: Bug Tracker, https://github.com/belfryscad/openscad_docsgen/issues
Project-URL: Releases, https://github.com/belfryscad/openscad_docsgen/releases
Project-URL: Usage, https://github.com/belfryscad/openscad_docsgen/README.rst
Project-URL: Documentation, https://github.com/belfryscad/openscad_docsgen/WRITING_DOCS.md
Author-email: Revar Desmera <revarbat@gmail.com>
Maintainer-email: Revar Desmera <revarbat@gmail.com>
License: MIT License
License-File: LICENSE
Keywords: docs generation,docsgen,documentation generation,openscad
Classifier: Development Status :: 5 - Production/Stable
Classifier: Environment :: Console
Classifier: Intended Audience :: Developers
Classifier: Intended Audience :: Manufacturing
Classifier: Operating System :: MacOS :: MacOS X
Classifier: Operating System :: Microsoft :: Windows
Classifier: Operating System :: POSIX
Classifier: Programming Language :: Python :: 3
Classifier: Topic :: Artistic Software
Classifier: Topic :: Multimedia :: Graphics :: 3D Modeling
Classifier: Topic :: Multimedia :: Graphics :: 3D Rendering
Classifier: Topic :: Software Development :: Libraries
Classifier: Topic :: Software Development :: Libraries :: Python Modules
Requires-Python: >=3.7
Requires-Dist: imageio>=2.37.0
Requires-Dist: openscad-runner>=1.2.2
Requires-Dist: pillow>=10.3.0
Requires-Dist: pyyaml>=6.0
Requires-Dist: scipy>=1.15.3
